khl/__init__.py
khl/_types.py
khl/api.py
khl/cert.py
khl/channel.py
khl/client.py
khl/context.py
khl/game.py
khl/gateway.py
khl/guild.py
khl/interface.py
khl/intimacy.py
khl/message.py
khl/permission.py
khl/ratelimiter.py
khl/receiver.py
khl/requester.py
khl/role.py
khl/user.py
khl/util.py
khl/bot/__init__.py
khl/bot/bot.py
khl/card/__init__.py
khl/card/card.py
khl/card/card_message.py
khl/card/color.py
khl/card/element.py
khl/card/interface.py
khl/card/module.py
khl/card/struct.py
khl/command/__init__.py
khl/command/command.py
khl/command/exception.py
khl/command/lexer.py
khl/command/manager.py
khl/command/parser.py
khl/command/rule.py
khl/command/util.py
khl/task/__init__.py
khl/task/manager.py
khl.py-0.3.17.dist-info/LICENSE
khl.py-0.3.17.dist-info/METADATA
khl.py-0.3.17.dist-info/WHEEL
khl.py-0.3.17.dist-info/top_level.txt
khl.py-0.3.17.dist-info/RECORD
