Metadata-Version: 2.1
Name: khl.py
Version: 0.3.17
Summary: Python SDK for kaiheila.cn API
Home-page: https://github.com/TWT233/khl.py
Author: TWT233
Author-email: TWT2333@outlook.com
License: UNKNOWN
Project-URL: Bug Tracker, https://github.com/TWT233/khl.py/issues
Project-URL: Tutorial, https://github.com/TWT233/khl.py/tree/main/example
Platform: UNKNOWN
Classifier: Programming Language :: Python :: 3
Classifier: License :: OSI Approved :: MIT License
Classifier: Operating System :: OS Independent
Requires-Python: >=3.6
License-File: LICENSE
